pytransform_vax_001289/__init__.py
pytransform_vax_001289/platforms/darwin/aarch64/_pytransform_vax_001289.dylib
pytransform_vax_001289/platforms/darwin/x86_64/_pytransform_vax_001289.dylib
pytransform_vax_001289/platforms/linux/x86/_pytransform_vax_001289.so
pytransform_vax_001289/platforms/linux/x86_64/_pytransform_vax_001289.so
yourbase/__init__.py
yourbase/acceleration.py
yourbase/boot.py
yourbase/cohorting.py
yourbase/config.py
yourbase/conflicts.py
yourbase/debugging.py
yourbase/helpers.py
yourbase/license.py
yourbase/metrics.py
yourbase/reporting.py
yourbase/tos.py
yourbase/utils.py
yourbase/yourbase-analysisd
yourbase/cli/__init__.py
yourbase/cli/ast.py
yourbase/cli/cache.py
yourbase/cli/graph.py
yourbase/cli/peek.py
yourbase/cli/testify.py
yourbase/cli/utils.py
yourbase/graph/__init__.py
yourbase/graph/dependency_graph.py
yourbase/graph/sqlite_function_graph.py
yourbase/plugins/__init__.py
yourbase/plugins/coverage.py
yourbase/plugins/pytest.py
yourbase/plugins/testify.py
yourbase/plugins/unittest.py
yourbase/snapshot/__init__.py
yourbase/snapshot/git.py
yourbase/snapshot/local.py
yourbase/snapshot/s3.py
yourbase/tracer/__init__.py
yourbase/tracer/cov_tracer.py
yourbase/tracer/tracer.py
yourbase-7.1.3.dist-info/LICENSE
yourbase-7.1.3.dist-info/METADATA
yourbase-7.1.3.dist-info/WHEEL
yourbase-7.1.3.dist-info/entry_points.txt
yourbase-7.1.3.dist-info/top_level.txt
yourbase-7.1.3.dist-info/RECORD
